[{"Visit_Date":"05/08/2020","Visit_Time":"16:25:29","Customer_ID":"1","Location_ID":"loc2","New_Customer":"YES","Sentiment":"happy"},{"Visit_Date":"05/08/2020","Visit_Time":"16:28:03","Customer_ID":"2","Location_ID":"loc2","New_Customer":"YES","Sentiment":"fear"},{"Visit_Date":"05/08/2020","Visit_Time":"16:28:22","Customer_ID":"1","Location_ID":"loc2","New_Customer":"NO","Sentiment":"fear"},{"Visit_Date":"05/08/2020","Visit_Time":"16:29:07","Customer_ID":"3","Location_ID":"loc2","New_Customer":"YES","Sentiment":"sad"},{"Visit_Date":"13/08/2020","Visit_Time":"19:46:06","Customer_ID":"1","Location_ID":"loc2","New_Customer":"NO","Sentiment":"happy"},{"Visit_Date":"13/08/2020","Visit_Time":"19:46:20","Customer_ID":"1","Location_ID":"loc2","New_Customer":"NO","Sentiment":"neutral"},{"Visit_Date":"14/08/2020","Visit_Time":"00:12:50","Customer_ID":"1","Location_ID":"loc2","New_Customer":"NO","Sentiment":"angry"},{"Visit_Date":"14/08/2020","Visit_Time":"00:21:23","Customer_ID":"1","Location_ID":"loc2","New_Customer":"NO","Sentiment":"angry"},{"Visit_Date":"14/08/2020","Visit_Time":"09:53:35","Customer_ID":"1","Location_ID":"loc2","New_Customer":"NO","Sentiment":"neutral"},{"Visit_Date":"14/08/2020","Visit_Time":"10:07:14","Customer_ID":"1","Location_ID":"loc2","New_Customer":"NO","Sentiment":"fear"},{"Visit_Date":"14/08/2020","Visit_Time":"10:07:30","Customer_ID":"2","Location_ID":"loc2","New_Customer":"NO","Sentiment":"happy"},{"Visit_Date":"14/08/2020","Visit_Time":"10:12:44","Customer_ID":"1","Location_ID":"loc2","New_Customer":"NO","Sentiment":"happy"},{"Visit_Date":"14/08/2020","Visit_Time":"10:16:59","Customer_ID":"1","Location_ID":"loc2","New_Customer":"NO","Sentiment":"neutral"},{"Visit_Date":"14/08/2020","Visit_Time":"14:06:29","Customer_ID":"1","Location_ID":"loc2","New_Customer":"NO","Sentiment":"happy"},{"Visit_Date":"14/08/2020","Visit_Time":"14:06:43","Customer_ID":"4","Location_ID":"loc2","New_Customer":"YES","Sentiment":"happy"}]